MANIFEST.in
README.md
requirements.txt
setup.cfg
setup.py
palantiri/BasePlotHandlers.py
palantiri/ClassificationPlotHandlers.py
palantiri/ClusteringPlotHandlers.py
palantiri/GraphPlotHandlers.py
palantiri/RegressionPlotHandlers.py
palantiri/RegretPlotHandler.py
palantiri/__init__.py
palantiri.egg-info/PKG-INFO
palantiri.egg-info/SOURCES.txt
palantiri.egg-info/dependency_links.txt
palantiri.egg-info/requires.txt
palantiri.egg-info/top_level.txt