Metadata-Version: 2.1
Name: palantiri
Version: 0.2.0
Summary: Out of the box visualisation tools
Home-page: https://github.com/wolfenfeld/palantiri
Author: Amit Wolfenfeld
Author-email: wolfenfeld@gmail.com
License: BSD
Download-URL: https://github.com/wolfenfeld/palantiri/tarball/0.2.0
Platform: UNKNOWN
Classifier: Development Status :: 3 - Alpha
Classifier: Intended Audience :: Developers
Classifier: Programming Language :: Python :: 3
